stjames/__init__.py
stjames/_deprecated_solvent_settings.py
stjames/atom.py
stjames/base.py
stjames/basis_set.py
stjames/calculation.py
stjames/compute_settings.py
stjames/conformers.py
stjames/constraint.py
stjames/correction.py
stjames/dna.py
stjames/engine.py
stjames/excited_state_settings.py
stjames/message.py
stjames/method.py
stjames/mode.py
stjames/molecule.py
stjames/opt_settings.py
stjames/pdb.py
stjames/periodic_cell.py
stjames/protein.py
stjames/py.typed
stjames/rna.py
stjames/scf_settings.py
stjames/settings.py
stjames/solvent.py
stjames/status.py
stjames/task.py
stjames/thermochem_settings.py
stjames/types.py
stjames/atomium_stjames/__init__.py
stjames/atomium_stjames/data.py
stjames/atomium_stjames/mmcif.py
stjames/atomium_stjames/pdb.py
stjames/atomium_stjames/utilities.py
stjames/data/__init__.py
stjames/data/bragg_radii.json
stjames/data/elements.py
stjames/data/isotopes.json
stjames/data/nist_isotopes.json
stjames/data/read_nist_isotopes.py
stjames/data/symbol_element.json
stjames/optimization/__init__.py
stjames/optimization/freezing_string_method.py
stjames/workflows/__init__.py
stjames/workflows/admet.py
stjames/workflows/basic_calculation.py
stjames/workflows/batch_docking.py
stjames/workflows/bde.py
stjames/workflows/conformer.py
stjames/workflows/conformer_search.py
stjames/workflows/descriptors.py
stjames/workflows/docking.py
stjames/workflows/double_ended_ts_search.py
stjames/workflows/electronic_properties.py
stjames/workflows/fukui.py
stjames/workflows/hydrogen_bond_basicity.py
stjames/workflows/ion_mobility.py
stjames/workflows/irc.py
stjames/workflows/macropka.py
stjames/workflows/membrane_permeability.py
stjames/workflows/molecular_dynamics.py
stjames/workflows/msa.py
stjames/workflows/multistage_opt.py
stjames/workflows/nmr.py
stjames/workflows/pka.py
stjames/workflows/pocket_detection.py
stjames/workflows/protein_binder_design.py
stjames/workflows/protein_cofolding.py
stjames/workflows/protein_md.py
stjames-0.0.156.dist-info/licenses/LICENSE
stjames-0.0.156.dist-info/METADATA
stjames-0.0.156.dist-info/WHEEL
stjames-0.0.156.dist-info/top_level.txt
stjames-0.0.156.dist-info/RECORD
