Metadata-Version: 2.4
Name: stjames
Version: 0.0.156
Summary: structured JSON atom/molecule encoding scheme
Project-URL: Homepage, https://github.com/rowansci/stjames
Project-URL: Bug Tracker, https://github.com/rowansci/stjames/issues
Requires-Python: >=3.11
License-File: LICENSE
Requires-Dist: pydantic>=2.4
Requires-Dist: numpy
Requires-Dist: requests
Requires-Dist: rdkit
Requires-Dist: more-itertools
Dynamic: license-file
